{"metaDados":{"consultaNome":"Cadastro - Pessoa Jur\u00eddica - B\u00e1sica","consultaUid":"direct-e1d01b48-9e00-482a-af92-6ef9bfb8a098","chave":"CNPJ=07854406000180;","usuario":"Rony Nogueira","mensagem":"Sucesso","ip":"191.25.244.150","resultadoId":1,"resultado":"Sucesso","apiVersao":"v3","enviarCallback":false,"gerarComprovante":false,"urlComprovante":null,"assincrono":false,"data":"02\/06\/2026 17:58:37","tempoExecucaoMs":1046},"retorno":{"cnpj":"07.854.406\/0001-80","razaoSocial":"JM CONSTRUTORA E INCORPORADORA LTDA","nomeFantasia":"JM CONSTRUTORA E INCORPORADORA","dataFundacao":"13\/02\/2006 00:00:00","cnaeCodigo":4120400,"cnaeDescricao":"Constru\u00e7\u00e3o de edif\u00edcios","cnaEsSecundarios":[],"quantidadeFuncionarios":1,"situacaoCadastral":"ATIVA","naturezaJuridicaCodigo":2062,"naturezaJuridicaDescricao":"Sociedade Empres\u00e1ria Limitada","naturezaJuridicaTipo":null,"porte":"MICRO EMPRESA","faixaFuncionarios":"At\u00e9 9 Funcion\u00e1rios","faixaFaturamento":"At\u00e9 R$ 240,0 Mil","matriz":true,"orgaoPublico":null,"ramo":null,"tipoEmpresa":"LTDA","telefones":[{"telefoneComDDD":"(62) 991741213","telemarketingBloqueado":null,"operadora":null,"tipoTelefone":null,"whatsApp":null},{"telefoneComDDD":"(62) 991536968","telemarketingBloqueado":null,"operadora":null,"tipoTelefone":null,"whatsApp":null}],"enderecos":[{"logradouro":"SANTOS DUMONT","numero":"814 A","complemento":"QUADRA 35     LOTE 28 A","bairro":"BAIRRO JUNDIAI","cidade":"ANAPOLIS","uf":"GO","cep":"75113-180"}],"emails":[{"enderecoEmail":"joselito.abadia@terra.com.br"}],"ultimaAtualizacaoPJ":null,"socios":[{"documento":"402.913.911-68","nome":"JOSELITO MOREIRA DABADIA","percentualParticipacao":null,"dataEntrada":"13\/02\/2006 00:00:00","cargo":"S\u00f3cio Administrador"}]}}