{"metaDados":{"consultaNome":"Cadastro - Pessoa Jur\u00eddica - B\u00e1sica","consultaUid":"direct-26ca68bd-bc05-4828-b1b6-0b2d5e3e1ceb","chave":"CNPJ=09204240000182;","usuario":"Rony Nogueira","mensagem":"Sucesso","ip":"191.25.244.150","resultadoId":1,"resultado":"Sucesso","apiVersao":"v3","enviarCallback":false,"gerarComprovante":false,"urlComprovante":null,"assincrono":false,"data":"02\/06\/2026 17:59:30","tempoExecucaoMs":413},"retorno":{"cnpj":"09.204.240\/0001-82","razaoSocial":"LOCPEL TERRAPLENAGEM E LOCACAO DE MAQUINAS LTDA","nomeFantasia":"LOCPEL TERRAPLENAGEM","dataFundacao":"14\/11\/2007 00:00:00","cnaeCodigo":4313400,"cnaeDescricao":"Obras de terraplenagem","cnaEsSecundarios":[],"quantidadeFuncionarios":15,"situacaoCadastral":"ATIVA","naturezaJuridicaCodigo":2062,"naturezaJuridicaDescricao":"Sociedade Empres\u00e1ria Limitada","naturezaJuridicaTipo":null,"porte":"MICRO EMPRESA","faixaFuncionarios":"De 5 A 100 Funcion\u00e1rios","faixaFaturamento":"De R$ 240,01 Mil A R$ 2,4 MM","matriz":true,"orgaoPublico":null,"ramo":null,"tipoEmpresa":"LTDA","telefones":[{"telefoneComDDD":"(62) 984891255","telemarketingBloqueado":null,"operadora":null,"tipoTelefone":null,"whatsApp":null},{"telefoneComDDD":"(62) 984471244","telemarketingBloqueado":null,"operadora":null,"tipoTelefone":null,"whatsApp":null},{"telefoneComDDD":"(62) 33210701","telemarketingBloqueado":null,"operadora":null,"tipoTelefone":null,"whatsApp":null},{"telefoneComDDD":"(62) 984471238","telemarketingBloqueado":null,"operadora":null,"tipoTelefone":null,"whatsApp":null},{"telefoneComDDD":"(62) 984751250","telemarketingBloqueado":null,"operadora":null,"tipoTelefone":null,"whatsApp":null}],"enderecos":[{"logradouro":"BRASIL","numero":"SN","complemento":"QUADRA44     LOTE 4","bairro":"PARQUE SAO JOAO","cidade":"ANAPOLIS","uf":"GO","cep":"75126-207"},{"logradouro":"BRASIL SUL","numero":"5865","complemento":null,"bairro":"BAIRRO SAO JOAO","cidade":"ANAPOLIS","uf":"GO","cep":"75124-820"}],"emails":[{"enderecoEmail":"locpelt@gmail.com"},{"enderecoEmail":"locpet@gmail.com"},{"enderecoEmail":"om.contabilidade@hotmail.com"}],"ultimaAtualizacaoPJ":null,"socios":[{"documento":"840.940.951-87","nome":"LEANDRO RODRIGUES PEIXOTO","percentualParticipacao":null,"dataEntrada":"14\/11\/2007 00:00:00","cargo":"S\u00f3cio Administrador"},{"documento":"931.542.831-53","nome":"LILIAN CRISTINA BARBARESCO DE ANDRADE PEIXOTO","percentualParticipacao":null,"dataEntrada":"03\/11\/2025 00:00:00","cargo":"S\u00f3cio Administrador"}]}}