{"metaDados":{"consultaNome":"Cadastro - Pessoa Jur\u00eddica - B\u00e1sica","consultaUid":"direct-5f894024-1123-4f44-869e-475a2e1b6816","chave":"CNPJ=17159229000176;","usuario":"Rony Nogueira","mensagem":"Sucesso","ip":"191.25.244.150","resultadoId":1,"resultado":"Sucesso","apiVersao":"v3","enviarCallback":false,"gerarComprovante":false,"urlComprovante":null,"assincrono":false,"data":"02\/06\/2026 18:05:25","tempoExecucaoMs":439},"retorno":{"cnpj":"17.159.229\/0001-76","razaoSocial":"LABORATORIO TEUTO BRASILEIRO S A","nomeFantasia":null,"dataFundacao":"08\/02\/1971 00:00:00","cnaeCodigo":2121101,"cnaeDescricao":"Fabrica\u00e7\u00e3o de medicamentos alop\u00e1ticos para uso humano","cnaEsSecundarios":[],"quantidadeFuncionarios":1176,"situacaoCadastral":"ATIVA","naturezaJuridicaCodigo":2054,"naturezaJuridicaDescricao":"Sociedade An\u00f4nima Fechada","naturezaJuridicaTipo":null,"porte":"GRANDE","faixaFuncionarios":"Mais Que 200 Funcion\u00e1rios","faixaFaturamento":"De R$ 400,1 MM A R$ 500,0 MM","matriz":true,"orgaoPublico":null,"ramo":null,"tipoEmpresa":"OUTRAS","telefones":[{"telefoneComDDD":"(48) 999881396","telemarketingBloqueado":null,"operadora":null,"tipoTelefone":null,"whatsApp":null},{"telefoneComDDD":"(43) 999550190","telemarketingBloqueado":null,"operadora":null,"tipoTelefone":null,"whatsApp":null},{"telefoneComDDD":"(11) 948155398","telemarketingBloqueado":null,"operadora":null,"tipoTelefone":null,"whatsApp":null},{"telefoneComDDD":"(82) 998110097","telemarketingBloqueado":null,"operadora":null,"tipoTelefone":null,"whatsApp":null},{"telefoneComDDD":"(28) 981020027","telemarketingBloqueado":null,"operadora":null,"tipoTelefone":null,"whatsApp":null}],"enderecos":[{"logradouro":"VP 7D MODULO 11","numero":"S N","complemento":"QUADRA13","bairro":"DAIA","cidade":"ANAPOLIS","uf":"GO","cep":"75132-140"}],"emails":[{"enderecoEmail":"fiscal@teuto.com.br"},{"enderecoEmail":"sastecffrr@uol.com.br"},{"enderecoEmail":"cim_unipar@hotmail.com"}],"ultimaAtualizacaoPJ":null,"socios":[{"documento":"477.029.906-00","nome":"MARCELO LEITE HENRIQUES","percentualParticipacao":null,"dataEntrada":"23\/12\/2010 00:00:00","cargo":"Presidente"},{"documento":"038.027.578-31","nome":"OSVALDO SOARES PINTO","percentualParticipacao":null,"dataEntrada":"23\/12\/2010 00:00:00","cargo":"Diretor"},{"documento":"433.831.065-00","nome":"LUIZ ALBERTO LYRA PINHEIRO","percentualParticipacao":null,"dataEntrada":"24\/01\/2019 00:00:00","cargo":"Diretor"},{"documento":"796.589.381-91","nome":"ANDREIA CAVALCANTE DA SILVA","percentualParticipacao":null,"dataEntrada":"13\/10\/2025 00:00:00","cargo":"Diretor"}]}}