{"metaDados":{"consultaNome":"Cadastro - Pessoa Jur\u00eddica - B\u00e1sica","consultaUid":"direct-a2bc9bf5-c182-4f38-b660-bee1ba98fc9a","chave":"CNPJ=22913457000120;","usuario":"Rony Nogueira","mensagem":"Sucesso","ip":"191.25.244.150","resultadoId":1,"resultado":"Sucesso","apiVersao":"v3","enviarCallback":false,"gerarComprovante":false,"urlComprovante":null,"assincrono":false,"data":"02\/06\/2026 18:12:28","tempoExecucaoMs":405},"retorno":{"cnpj":"22.913.457\/0001-20","razaoSocial":"DOUTOR DA CONSTRUCAO LTDA","nomeFantasia":"DOUTOR DA CONSTRUCAO","dataFundacao":"23\/07\/2015 00:00:00","cnaeCodigo":4330404,"cnaeDescricao":"Servi\u00e7os de pintura de edif\u00edcios em geral","cnaEsSecundarios":[],"quantidadeFuncionarios":4,"situacaoCadastral":"ATIVA","naturezaJuridicaCodigo":2062,"naturezaJuridicaDescricao":"Sociedade Empres\u00e1ria Limitada","naturezaJuridicaTipo":null,"porte":"MICRO EMPRESA","faixaFuncionarios":"At\u00e9 9 Funcion\u00e1rios","faixaFaturamento":"At\u00e9 R$ 240,0 Mil","matriz":true,"orgaoPublico":null,"ramo":null,"tipoEmpresa":"LTDA","telefones":[{"telefoneComDDD":"(62) 33114669","telemarketingBloqueado":null,"operadora":null,"tipoTelefone":null,"whatsApp":null}],"enderecos":[{"logradouro":"SAO PAULO","numero":"SN","complemento":"QUADRA G LOTE 1 A SALA 2","bairro":"SETOR INDUSTRIAL AEROPORTO","cidade":"ANAPOLIS","uf":"GO","cep":"75104-350"}],"emails":[{"enderecoEmail":"doutordaconstrucao@outlook.com"}],"ultimaAtualizacaoPJ":null,"socios":[{"documento":"917.892.811-72","nome":"SHIRLENE DA COSTA RODRIGUES","percentualParticipacao":null,"dataEntrada":"23\/07\/2015 00:00:00","cargo":"S\u00f3cio Administrador"}]}}