{"metaDados":{"consultaNome":"Cadastro - Pessoa Jur\u00eddica - B\u00e1sica","consultaUid":"direct-627b5422-8e42-455c-88fa-7d89bb6ccc0b","chave":"CNPJ=26480510000105;","usuario":"Rony Nogueira","mensagem":"Sucesso","ip":"191.25.244.150","resultadoId":1,"resultado":"Sucesso","apiVersao":"v3","enviarCallback":false,"gerarComprovante":false,"urlComprovante":null,"assincrono":false,"data":"02\/06\/2026 18:14:59","tempoExecucaoMs":435},"retorno":{"cnpj":"26.480.510\/0001-05","razaoSocial":"CLAUDINEY FONSECA IMOVEIS LTDA","nomeFantasia":"CLAUDINEY IMOVEIS","dataFundacao":"04\/11\/2016 00:00:00","cnaeCodigo":6821801,"cnaeDescricao":"Corretagem na compra e venda e avalia\u00e7\u00e3o de im\u00f3veis","cnaEsSecundarios":[],"quantidadeFuncionarios":1,"situacaoCadastral":"ATIVA","naturezaJuridicaCodigo":2062,"naturezaJuridicaDescricao":"Sociedade Empres\u00e1ria Limitada","naturezaJuridicaTipo":null,"porte":"MICRO EMPRESA","faixaFuncionarios":"At\u00e9 9 Funcion\u00e1rios","faixaFaturamento":"At\u00e9 R$ 240,0 Mil","matriz":true,"orgaoPublico":null,"ramo":null,"tipoEmpresa":"LTDA","telefones":[{"telefoneComDDD":"(62) 991092410","telemarketingBloqueado":null,"operadora":null,"tipoTelefone":null,"whatsApp":null},{"telefoneComDDD":"(62) 991096124","telemarketingBloqueado":null,"operadora":null,"tipoTelefone":null,"whatsApp":null},{"telefoneComDDD":"(62) 991511049","telemarketingBloqueado":null,"operadora":null,"tipoTelefone":null,"whatsApp":null}],"enderecos":[{"logradouro":"DESEMBARGADOR JAIME","numero":"219","complemento":"SALA 05","bairro":"SETOR CENTRAL","cidade":"ANAPOLIS","uf":"GO","cep":"75020-040"}],"emails":[{"enderecoEmail":"claudineyaugusto@hotmail.com"},{"enderecoEmail":"felipecarneiro14@hotmail.com"}],"ultimaAtualizacaoPJ":null,"socios":[{"documento":"586.462.301-63","nome":"CLAUDINEY AUGUSTO DA FONSECA","percentualParticipacao":null,"dataEntrada":"04\/11\/2016 00:00:00","cargo":"S\u00f3cio Administrador"}]}}