{"metaDados":{"consultaNome":"Cadastro - Pessoa Jur\u00eddica - B\u00e1sica","consultaUid":"direct-b6f723f8-fc1d-44c7-9abe-4647252b8a04","chave":"CNPJ=30037109000164;","usuario":"Rony Nogueira","mensagem":"Sucesso","ip":"191.25.244.150","resultadoId":1,"resultado":"Sucesso","apiVersao":"v3","enviarCallback":false,"gerarComprovante":false,"urlComprovante":null,"assincrono":false,"data":"02\/06\/2026 18:19:02","tempoExecucaoMs":1001},"retorno":{"cnpj":"30.037.109\/0001-64","razaoSocial":"MUNDIAL MADEIRAS LTDA","nomeFantasia":"MUNDIAL MADEIRAS","dataFundacao":"26\/03\/2018 00:00:00","cnaeCodigo":4744002,"cnaeDescricao":"Com\u00e9rcio varejista de madeira e artefatos","cnaEsSecundarios":[],"quantidadeFuncionarios":7,"situacaoCadastral":"ATIVA","naturezaJuridicaCodigo":2062,"naturezaJuridicaDescricao":"Sociedade Empres\u00e1ria Limitada","naturezaJuridicaTipo":null,"porte":"MICRO EMPRESA","faixaFuncionarios":"At\u00e9 9 Funcion\u00e1rios","faixaFaturamento":"De R$ 240,01 Mil A R$ 2,4 MM","matriz":true,"orgaoPublico":null,"ramo":null,"tipoEmpresa":"LTDA","telefones":[{"telefoneComDDD":"(62) 991786180","telemarketingBloqueado":null,"operadora":null,"tipoTelefone":null,"whatsApp":null},{"telefoneComDDD":"(62) 30983060","telemarketingBloqueado":null,"operadora":null,"tipoTelefone":null,"whatsApp":null},{"telefoneComDDD":"(62) 39434488","telemarketingBloqueado":null,"operadora":null,"tipoTelefone":null,"whatsApp":null}],"enderecos":[{"logradouro":"BRASIL","numero":"1375","complemento":"QUADRA07     LOTE 91","bairro":"CIDADE JARDIM","cidade":"ANAPOLIS","uf":"GO","cep":"75080-240"}],"emails":[{"enderecoEmail":"financeiromundialmadeiras@yahoo.com"}],"ultimaAtualizacaoPJ":null,"socios":[{"documento":"560.396.381-68","nome":"LUCIANO GONCALVES DE OLIVEIRA","percentualParticipacao":null,"dataEntrada":"26\/03\/2018 00:00:00","cargo":"S\u00f3cio Administrador"},{"documento":"912.293.321-20","nome":"NILZA DA SILVA CORREIA OLIVEIRA","percentualParticipacao":null,"dataEntrada":"26\/03\/2018 00:00:00","cargo":"S\u00f3cio Administrador"}]}}