{"metaDados":{"consultaNome":"Cadastro - Pessoa Jur\u00eddica - B\u00e1sica","consultaUid":"direct-ecd9bef3-3dbc-43fe-bdfd-4ffbfc83ff9d","chave":"CNPJ=37556572000161;","usuario":"Rony Nogueira","mensagem":"Sucesso","ip":"191.25.244.150","resultadoId":1,"resultado":"Sucesso","apiVersao":"v3","enviarCallback":false,"gerarComprovante":false,"urlComprovante":null,"assincrono":false,"data":"02\/06\/2026 18:25:44","tempoExecucaoMs":430},"retorno":{"cnpj":"37.556.572\/0001-61","razaoSocial":"DUO CANNON INOVACAO TECNOLOGICA LTDA","nomeFantasia":"DUO CANNON","dataFundacao":"29\/06\/2020 00:00:00","cnaeCodigo":4322302,"cnaeDescricao":"Instala\u00e7\u00e3o e manuten\u00e7\u00e3o de sistemas centrais de ar condicionado, de ventila\u00e7\u00e3o e refrigera\u00e7\u00e3o","cnaEsSecundarios":[],"quantidadeFuncionarios":null,"situacaoCadastral":"ATIVA","naturezaJuridicaCodigo":2062,"naturezaJuridicaDescricao":"Sociedade Empres\u00e1ria Limitada","naturezaJuridicaTipo":null,"porte":"EMPRESA DE PEQUENO PORTE","faixaFuncionarios":"At\u00e9 9 Funcion\u00e1rios","faixaFaturamento":"At\u00e9 R$ 240,0 Mil","matriz":true,"orgaoPublico":null,"ramo":null,"tipoEmpresa":"LTDA","telefones":[{"telefoneComDDD":"(62) 981794972","telemarketingBloqueado":null,"operadora":null,"tipoTelefone":null,"whatsApp":null}],"enderecos":[{"logradouro":"ELIZEU JORGE CAMPOS","numero":"275","complemento":"QUADRA15A     LOTE 26","bairro":"VILA GOIS","cidade":"ANAPOLIS","uf":"GO","cep":"75120-110"}],"emails":[{"enderecoEmail":"kelly@sollaren.com.br"},{"enderecoEmail":"kellyknm@hotmail.com"}],"ultimaAtualizacaoPJ":null,"socios":[{"documento":"140.115.968-09","nome":"CLAUDIO FELICIANO DE OLIVEIRA","percentualParticipacao":null,"dataEntrada":"09\/02\/2026 00:00:00","cargo":"S\u00f3cio Administrador"}]}}