{"metaDados":{"consultaNome":"Cadastro - Pessoa Jur\u00eddica - B\u00e1sica","consultaUid":"direct-90a096bd-a481-4cb7-920e-58964a50c6d1","chave":"CNPJ=37743439000114;","usuario":"Rony Nogueira","mensagem":"Sucesso","ip":"191.25.244.150","resultadoId":1,"resultado":"Sucesso","apiVersao":"v3","enviarCallback":false,"gerarComprovante":false,"urlComprovante":null,"assincrono":false,"data":"02\/06\/2026 18:25:57","tempoExecucaoMs":399},"retorno":{"cnpj":"37.743.439\/0001-14","razaoSocial":"RAZZA CONSTRUTORA E INCORPORADORA LTDA","nomeFantasia":"RAZZA CONSTRUTORA","dataFundacao":"16\/07\/2020 00:00:00","cnaeCodigo":4110700,"cnaeDescricao":"Incorpora\u00e7\u00e3o de empreendimentos imobili\u00e1rios","cnaEsSecundarios":[],"quantidadeFuncionarios":null,"situacaoCadastral":"ATIVA","naturezaJuridicaCodigo":2062,"naturezaJuridicaDescricao":"Sociedade Empres\u00e1ria Limitada","naturezaJuridicaTipo":null,"porte":"PEQUENA","faixaFuncionarios":"At\u00e9 9 Funcion\u00e1rios","faixaFaturamento":"At\u00e9 R$ 240,0 Mil","matriz":true,"orgaoPublico":null,"ramo":null,"tipoEmpresa":"LTDA","telefones":[{"telefoneComDDD":"(62) 981065114","telemarketingBloqueado":null,"operadora":null,"tipoTelefone":null,"whatsApp":null},{"telefoneComDDD":"(62) 992027695","telemarketingBloqueado":null,"operadora":null,"tipoTelefone":null,"whatsApp":null},{"telefoneComDDD":"(62) 30995814","telemarketingBloqueado":null,"operadora":null,"tipoTelefone":null,"whatsApp":null}],"enderecos":[{"logradouro":"COMERCIAL","numero":"SN","complemento":"QUADRA25     LOTE 56     SALA 04","bairro":"PARQUE BRASILIA 2 ETAPA","cidade":"ANAPOLIS","uf":"GO","cep":"75093-715"},{"logradouro":"AYRTON SENNA DA SILVA","numero":"503","complemento":"QUADRA04     LOTE 22     SALA 02","bairro":"PARQUE SAO JERONIMO","cidade":"ANAPOLIS","uf":"GO","cep":"75097-000"}],"emails":[{"enderecoEmail":"contato@razzaconstrutora.com.br"}],"ultimaAtualizacaoPJ":null,"socios":[{"documento":"48.429.384\/0001-99","nome":"AMF HOLDING E PARTICIPACOES LTDA","percentualParticipacao":null,"dataEntrada":"31\/03\/2026 00:00:00","cargo":"S\u00f3cio"},{"documento":"700.876.411-19","nome":"ARTHUR DA COSTA MOREIRA","percentualParticipacao":null,"dataEntrada":"31\/03\/2026 00:00:00","cargo":"Administrador"}]}}